Metadata-Version: 2.1
Name: truthdiscovery
Version: 1.0.4
Summary: Python3 library implementing a selection of truth discoveryalgorithms
Home-page: https://github.com/joesingo/truthdiscovery
Author: Joe Singleton
Author-email: joesingo@gmail.com
Requires-Python: >=3.5
License-File: LICENSE
Requires-Dist: attrs (==22.2.0)
Requires-Dist: bidict (==0.22.1)
Requires-Dist: click (==8.1.3)
Requires-Dist: contourpy (==1.0.7)
Requires-Dist: coverage (==7.2.2)
Requires-Dist: cycler (==0.11.0)
Requires-Dist: exceptiongroup (==1.1.1)
Requires-Dist: Flask (==2.2.3)
Requires-Dist: fonttools (==4.39.3)
Requires-Dist: imageio (==2.27.0)
Requires-Dist: iniconfig (==2.0.0)
Requires-Dist: itsdangerous (==2.1.2)
Requires-Dist: Jinja2 (==3.1.2)
Requires-Dist: kiwisolver (==1.4.4)
Requires-Dist: MarkupSafe (==2.1.2)
Requires-Dist: matplotlib (==3.7.1)
Requires-Dist: numpy (==1.24.2)
Requires-Dist: packaging (==23.0)
Requires-Dist: Pillow (==9.4.0)
Requires-Dist: pluggy (==1.0.0)
Requires-Dist: pycairo (==1.23.0)
Requires-Dist: pycodestyle (==2.10.0)
Requires-Dist: pyparsing (==3.0.9)
Requires-Dist: pytest (==7.2.2)
Requires-Dist: python-dateutil (==2.8.2)
Requires-Dist: PyYAML (==6.0)
Requires-Dist: scipy (==1.10.1)
Requires-Dist: six (==1.16.0)
Requires-Dist: tifffile (==2023.3.21)
Requires-Dist: tomli (==2.0.1)
Requires-Dist: Werkzeug (==2.2.3)
